README.md
setup.py
mallerenga/__init__.py
mallerenga.egg-info/PKG-INFO
mallerenga.egg-info/SOURCES.txt
mallerenga.egg-info/dependency_links.txt
mallerenga.egg-info/requires.txt
mallerenga.egg-info/top_level.txt
mallerenga/twitter/__init__.py
mallerenga/twitter/status.py
mallerenga/twitter/twitter.py
mallerenga/twitter/utils.py