Metadata-Version: 2.1
Name: mallerenga
Version: 0.1.0
Summary: Handle Twitter accounts
Home-page: https://github.com/pybcn/mallerenga
Author: Ignasi Fosch
Author-email: natx@y10k.ws
License: MIT
Platform: UNKNOWN
Classifier: License :: OSI Approved :: MIT License
Classifier: Programming Language :: Python :: 3
Classifier: Programming Language :: Python :: 3.6
Classifier: Programming Language :: Python :: 3.7
